LICENSE
README.md
setup.py
noolite_mqtt/__init__.py
noolite_mqtt/enums.py
noolite_mqtt/hass_discover.py
noolite_mqtt/noolite_cli.py
noolite_mqtt/noolite_f_cli.py
noolite_mqtt/noolite_rx_bind.py
noolite_mqtt/noolite_serial.py
noolite_mqtt.egg-info/PKG-INFO
noolite_mqtt.egg-info/SOURCES.txt
noolite_mqtt.egg-info/dependency_links.txt
noolite_mqtt.egg-info/entry_points.txt
noolite_mqtt.egg-info/requires.txt
noolite_mqtt.egg-info/top_level.txt