Metadata-Version: 2.1
Name: noolite-mqtt
Version: 0.1.3
Summary: NooLite MQTT binding
Home-page: https://github.com/foxel/noolite-mqtt-python
Author: Andrey F. Kupreychik
Author-email: foxel@quickfox.ru
License: UNKNOWN
Platform: UNKNOWN
Classifier: Programming Language :: Python :: 3
Classifier: Programming Language :: Python :: 3.5
Classifier: Programming Language :: Python :: 3.6
Classifier: License :: OSI Approved :: MIT License
Classifier: Operating System :: OS Independent
License-File: LICENSE
